{
  "gitSyncId": "67811a5458792a13d9b88165_1af569ba-663f-4503-9450-8adcf18d38fa",
  "id": "Form Input BAB_Total_record_public_bab1",
  "pluginId": "postgres-plugin",
  "pluginType": "DB",
  "unpublishedAction": {
    "actionConfiguration": {
      "body": "SELECT COUNT(*) from public.bab;",
      "encodeParamsToggle": true,
      "paginationType": "NONE",
      "pluginSpecifiedTemplates": [
        {
          "value": false
        }
      ],
      "timeoutInMillisecond": 10000
    },
    "confirmBeforeExecute": false,
    "datasource": {
      "id": "db_peraturan_final",
      "isAutoGenerated": false,
      "name": "db_peraturan_final",
      "pluginId": "postgres-plugin"
    },
    "dynamicBindingPathList": [
      {
        "key": "body"
      }
    ],
    "executeOnLoad": false,
    "name": "Total_record_public_bab1",
    "pageId": "Form Input BAB",
    "userSetOnLoad": false
  }
}