{
  "gitSyncId": "67811a5458792a13d9b88165_53762917-0e39-4403-af1e-d7b854755911",
  "id": "Form Input Peraturan_Triggern8n.Button1onClick",
  "pluginId": "js-plugin",
  "pluginType": "JS",
  "unpublishedAction": {
    "actionConfiguration": {
      "encodeParamsToggle": true,
      "jsArguments": [],
      "paginationType": "NONE",
      "timeoutInMillisecond": 10000
    },
    "clientSideExecution": true,
    "collectionId": "Form Input Peraturan_Triggern8n",
    "confirmBeforeExecute": false,
    "datasource": {
      "isAutoGenerated": false,
      "name": "UNUSED_DATASOURCE",
      "pluginId": "js-plugin"
    },
    "dynamicBindingPathList": [
      {
        "key": "body"
      }
    ],
    "executeOnLoad": false,
    "fullyQualifiedName": "Triggern8n.Button1onClick",
    "name": "Button1onClick",
    "pageId": "Form Input Peraturan",
    "userSetOnLoad": false
  }
}